beemo/__init__.py
beemo/post_types.py
beemo/scribe.py
beemo/settings.py
beemo/utils.py
beemo-0.3.2.dist-info/LICENSE.txt
beemo-0.3.2.dist-info/METADATA
beemo-0.3.2.dist-info/WHEEL
beemo-0.3.2.dist-info/entry_points.txt
beemo-0.3.2.dist-info/RECORD
