Metadata-Version: 2.3
Name: beemo
Version: 0.3.2
Summary: A Python-based static site generator. Bring your own content and templates and it'll quickly generate you a deployable HTML website/blog.
License: BSD-3-Clause
Author: Ben Nuttall
Author-email: ben@bennuttall.com
Requires-Python: >=3.10
Classifier: Development Status :: 4 - Beta
Requires-Dist: beautifulsoup4 (>=4.13.4,<5.0.0)
Requires-Dist: chameleon (>=4.6.0,<5.0.0)
Requires-Dist: docutils (>=0.22,<0.23)
Requires-Dist: markdown (>=3.8.2,<4.0.0)
Requires-Dist: pydantic (>=2.11.7,<3.0.0)
Requires-Dist: pydantic-settings (>=2.10.1,<3.0.0)
Requires-Dist: pyyaml (>=6.0.2)
Requires-Dist: structlog (>=25.4.0)
Project-URL: Issues, https://github.com/bennuttall/beemo/issues
Project-URL: Source, https://github.com/bennuttall/beemo
